LICENSE.txt
MANIFEST.in
README.md
pyproject.toml
setup.cfg
setup.py
petra_viewer/__init__.py
petra_viewer/data_pool.py
petra_viewer/default_settings.ini
petra_viewer/lookandfeel.py
petra_viewer/main_window.py
petra_viewer/petra_viewer.desktop
petra_viewer/petra_viewer.sh
petra_viewer/release.py
petra_viewer/test_settings.ini
petra_viewer.egg-info/PKG-INFO
petra_viewer.egg-info/SOURCES.txt
petra_viewer.egg-info/dependency_links.txt
petra_viewer.egg-info/entry_points.txt
petra_viewer.egg-info/requires.txt
petra_viewer.egg-info/top_level.txt
petra_viewer/asapo_tree_view/__init__.py
petra_viewer/asapo_tree_view/asapo_entries_class.py
petra_viewer/asapo_tree_view/asapo_table_headers.py
petra_viewer/asapo_tree_view/asapo_table_model.py
petra_viewer/convertor/__init__.py
petra_viewer/convertor/convert.py
petra_viewer/convertor/p23lib.py
petra_viewer/data_sources/__init__.py
petra_viewer/data_sources/asapo/__init__.py
petra_viewer/data_sources/asapo/asapo_data_set.py
petra_viewer/data_sources/asapo/asapo_data_set_setup.py
petra_viewer/data_sources/base_classes/__init__.py
petra_viewer/data_sources/base_classes/base_2d_detector.py
petra_viewer/data_sources/base_classes/base_2d_detector_setup.py
petra_viewer/data_sources/base_classes/base_data_set.py
petra_viewer/data_sources/beamview/__init__.py
petra_viewer/data_sources/beamview/beamview_data_set.py
petra_viewer/data_sources/p11scan/__init__.py
petra_viewer/data_sources/p11scan/p11scan_data_set.py
petra_viewer/data_sources/p11scan/p11scan_data_set_setup.py
petra_viewer/data_sources/p23scan/__init__.py
petra_viewer/data_sources/p23scan/p23scan_data_set.py
petra_viewer/data_sources/p23scan/p23scan_data_set_setup.py
petra_viewer/data_sources/reciprocal/__init__.py
petra_viewer/data_sources/reciprocal/reciprocal_data_set.py
petra_viewer/data_sources/test_datasets/__init__.py
petra_viewer/data_sources/test_datasets/test_datasets.py
petra_viewer/gui/__init__.py
petra_viewer/gui/about_dialog_ui.py
petra_viewer/gui/array_selector_ui.py
petra_viewer/gui/asapo_browser_ui.py
petra_viewer/gui/axis_selector_ui.py
petra_viewer/gui/base_2d_setup_ui.py
petra_viewer/gui/batch_ui.py
petra_viewer/gui/converter_ui.py
petra_viewer/gui/cube_view_ui.py
