Metadata-Version: 2.1
Name: petra-viewer
Version: 1.4.3
Summary: Simple viewer of data, acquired by xray-detectors at PETRA3
Home-page: UNKNOWN
Author: Yury Matveev
Author-email: yury.matveev@desy.de
License: GPLv3
Download-URL: https://pypi.org/project/petra-viewer/
Platform: Linux
Platform: Windows XP/Vista/7/8/10
Classifier: License :: OSI Approved :: GNU General Public License v3 (GPLv3)
Classifier: Programming Language :: Python
Classifier: Programming Language :: Python :: 3
Classifier: Programming Language :: Python :: 3.7
Classifier: Programming Language :: Python :: Implementation :: CPython
Classifier: Development Status :: 3 - Alpha
Requires-Python: >=3.7
Provides-Extra: 3D
Provides-Extra: ASAPO
Provides-Extra: CONVERTER
Provides-Extra: SILX
